CHANGELOG.rst
LICENSE
MANIFEST.in
README.rst
python-krbcontext.spec
requirements.txt
setup.cfg
setup.py
test-requirements.txt
tox.ini
docs/Makefile
docs/source/api.rst
docs/source/conf.py
docs/source/index.rst
docs/source/release-notes.rst
docs/source/usage.rst
krbcontext/__init__.py
krbcontext/context.py
krbcontext.egg-info/PKG-INFO
krbcontext.egg-info/SOURCES.txt
krbcontext.egg-info/dependency_links.txt
krbcontext.egg-info/requires.txt
krbcontext.egg-info/top_level.txt
scripts/make_release.sh
scripts/publish-packages.sh
test/test_krbcontext.py